Workbook

Sheet README
A1: Title:
A2: U.S. Housing Affordability and Macroeconomic Pressure (1985–2025)
A4: Research Question:
A5: How has housing affordability evolved relative to income, inflation, and interest rates?
A7: Core Hypothesis:
A8: Housing prices have decoupled from income growth due to structural supply constraints and monetary conditions.
A10: Data Sources:
A11: ="- U.S. Census Bureau (Income, Housing Prices)" -> - U.S. Census Bureau (Income, Housing Prices)
A12: ="- BLS CPI (Inflation)" -> - BLS CPI (Inflation)
A13: ="- FRED Mortgage Rates" -> - FRED Mortgage Rates
A15: Methodology:
A16: - All series annualized
A17: - Indexed to base year (1985 = 100)
A18: - Constructed affordability metrics:
A19: • Price-to-Income Ratio
A20: • Real Housing Index (CPI-adjusted)
A21: • Mortgage-Adjusted Affordability Pressure Index
A23: Author:
A24: Andy Setser

Sheet DATA_DICTIONARY
A1: Variable | B1: Definition | C1: Source | D1: Type
A2: Home Price | B2: Median US home sale price | C2: Census | D2: Level
A3: Income | B3: Median household income | C3: Census | D3: Level
A4: CPI | B4: Consumer Price Index | C4: BLS | D4: Price Index
A5: Mortgage Rate | B5: 30-year fixed rate | C5: FRED | D5: Interest rate

Sheet Raw Series
A1: Year | B1: Median Home Price | C1: Median Income | D1: CPI Index | E1: Mortgage Rate
A2: Annual time index used to align macroeconomic series into consistent yearly observations. | B2: Median annual home price estimate representing typical U.S. housing transaction values. Used as nominal housing cost measure in affordability calculations. | C2: Median household income representing central tendency of U.S. earnings distribution. Used as primary measure of purchasing power in affordability analysis. | D2: Consumer Price Index for All Urban Consumers (CPI-U), used as a general measure of price level changes over time. Serves as deflator for real housing price construction. | E2: 30-year fixed mortgage rate representing average borrowing cost in U.S. housing finance markets. Used as proxy for credit conditions affecting affordability.
A3: 1985 | B3: 84275 | C3: 61570 | D3: 107.6 | E3: 12.43
A4: 1986 | B4: 92025 | C4: 63850 | D4: 109.692 | E4: 10.19
A5: 1987 | B5: 104700 | C5: 64650 | D5: 113.617 | E5: 10.21
A6: 1988 | B6: 112225 | C6: 65130 | D6: 118.275 | E6: 10.34
A7: 1989 | B7: 120425 | C7: 66240 | D7: 123.942 | E7: 10.32
A8: 1990 | B8: 122300 | C8: 65440 | D8: 130.658 | E8: 10.13
A9: 1991 | B9: 119975 | C9: 63530 | D9: 136.167 | E9: 9.25
A10: 1992 | B10: 121375 | C10: 63010 | D10: 140.308 | E10: 8.39
A11: 1993 | B11: 126500 | C11: 62700 | D11: 144.475 | E11: 7.31
A12: 1994 | B12: 130425 | C12: 63370 | D12: 148.225 | E12: 8.38
A13: 1995 | B13: 133475 | C13: 65380 | D13: 152.383 | E13: 7.93
A14: 1996 | B14: 140250 | C14: 66340 | D14: 156.858 | E14: 7.81
... A42: 2024 | B42: 418975 | C42: 83730 | D42: 313.698 | E42: 6.72
A43: 2025
B45: https://fred.stlouisfed.org/series/MSPUS

Sheet Transformed Series
A1: Year | B1: Median Home Price | C1: Median Income | D1: CPI Index | E1: Mortgage Rate | F1: Price/Income | G1: Real Home Price (CPI Adjusted) | H1: Home price YoY% | I1: Income YoY% | J1: Log(Home Price) | K1: Log(Income) | L1: Affordability Index (1985=100) | M1: Rate Pressure Index
A2: 1985 | B2: 84275 | C2: 61570 | D2: 107.6 | E2: 12.43 | F2: =B2/C2 -> 1.3687673 | G2: =(B2/D2)*100 -> 78322.491 | J2: =LN(B2) -> 11.341841 | K2: =LN(C2) -> 11.02793 | L2: =(F2/$F$2)*100 -> 100 | M2: =E2*F2 -> 17.013777
A3: 1986 | B3: 92025 | C3: 63850 | D3: 109.692 | E3: 10.19 | F3: =B3/C3 -> 1.4412686 | G3: =(B3/D3)*100 -> 83893.994 | H3: =(B3-B2)/B2 -> 0.091960842 | I3: =(C3-C2)/C2 -> 0.037031022 | J3: =LN(B3) -> 11.429816 | K3: =LN(C3) -> 11.064292 | L3: =(F3/$F$2)*100 -> 105.29683 | M3: =E3*F3 -> 14.686527
A4: 1987 | B4: 104700 | C4: 64650 | D4: 113.617 | E4: 10.21 | F4: =B4/C4 -> 1.6194896 | G4: =(B4/D4)*100 -> 92151.703 | H4: =(B4-B3)/B3 -> 0.13773431 | I4: =(C4-C3)/C3 -> 0.012529366 | J4: =LN(B4) -> 11.558854 | K4: =LN(C4) -> 11.076743 | L4: =(F4/$F$2)*100 -> 118.31738 | M4: =E4*F4 -> 16.534988
A5: 1988 | B5: 112225 | C5: 65130 | D5: 118.275 | E5: 10.34 | F5: =B5/C5 -> 1.7230923 | G5: =(B5/D5)*100 -> 94884.802 | H5: =(B5-B4)/B4 -> 0.071872015 | I5: =(C5-C4)/C4 -> 0.007424594 | J5: =LN(B5) -> 11.628261 | K5: =LN(C5) -> 11.084141 | L5: =(F5/$F$2)*100 -> 125.88643 | M5: =E5*F5 -> 17.816774
A6: 1989 | B6: 120425 | C6: 66240 | D6: 123.942 | E6: 10.32 | F6: =B6/C6 -> 1.8180103 | G6: =(B6/D6)*100 -> 97162.382 | H6: =(B6-B5)/B5 -> 0.073067498 | I6: =(C6-C5)/C5 -> 0.017042837 | J6: =LN(B6) -> 11.698782 | K6: =LN(C6) -> 11.10104 | L6: =(F6/$F$2)*100 -> 132.82099 | M6: =E6*F6 -> 18.761866
A7: 1990 | B7: 122300 | C7: 65440 | D7: 130.658 | E7: 10.13 | F7: =B7/C7 -> 1.8688875 | G7: =(B7/D7)*100 -> 93603.147 | H7: =(B7-B6)/B6 -> 0.015569857 | I7: =(C7-C6)/C6 -> -0.012077295 | J7: =LN(B7) -> 11.714232 | K7: =LN(C7) -> 11.088889 | L7: =(F7/$F$2)*100 -> 136.53801 | M7: =E7*F7 -> 18.931831
A8: 1991 | B8: 119975 | C8: 63530 | D8: 136.167 | E8: 9.25 | F8: =B8/C8 -> 1.8884779 | G8: =(B8/D8)*100 -> 88108.719 | H8: =(B8-B7)/B7 -> -0.01901063 | I8: =(C8-C7)/C7 -> -0.029187042 | J8: =LN(B8) -> 11.695039 | K8: =LN(C8) -> 11.059268 | L8: =(F8/$F$2)*100 -> 137.96925 | M8: =E8*F8 -> 17.46842
A9: 1992 | B9: 121375 | C9: 63010 | D9: 140.308 | E9: 8.39 | F9: =B9/C9 -> 1.9262815 | G9: =(B9/D9)*100 -> 86506.115 | H9: =(B9-B8)/B8 -> 0.011669098 | I9: =(C9-C8)/C8 -> -0.0081851094 | J9: =LN(B9) -> 11.70664 | K9: =LN(C9) -> 11.051049 | L9: =(F9/$F$2)*100 -> 140.73112 | M9: =E9*F9 -> 16.161502
A10: 1993 | B10: 126500 | C10: 62700 | D10: 144.475 | E10: 7.31 | F10: =B10/C10 -> 2.0175439 | G10: =(B10/D10)*100 -> 87558.401 | H10: =(B10-B9)/B9 -> 0.042224511 | I10: =(C10-C9)/C9 -> -0.004919854 | J10: =LN(B10) -> 11.747998 | K10: =LN(C10) -> 11.046117 | L10: =(F10/$F$2)*100 -> 147.39861 | M10: =E10*F10 -> 14.748246
A11: 1994 | B11: 130425 | C11: 63370 | D11: 148.225 | E11: 8.38 | F11: =B11/C11 -> 2.0581505 | G11: =(B11/D11)*100 -> 87991.23 | H11: =(B11-B10)/B10 -> 0.031027668 | I11: =(C11-C10)/C10 -> 0.010685805 | J11: =LN(B11) -> 11.778554 | K11: =LN(C11) -> 11.056746 | L11: =(F11/$F$2)*100 -> 150.36527 | M11: =E11*F11 -> 17.247302
A12: 1995 | B12: 133475 | C12: 65380 | D12: 152.383 | E12: 7.93 | F12: =B12/C12 -> 2.0415265 | G12: =(B12/D12)*100 -> 87591.792 | H12: =(B12-B11)/B11 -> 0.023385087 | I12: =(C12-C11)/C11 -> 0.031718479 | J12: =LN(B12) -> 11.801669 | K12: =LN(C12) -> 11.087972 | L12: =(F12/$F$2)*100 -> 149.15074 | M12: =E12*F12 -> 16.189305
A13: 1996 | B13: 140250 | C13: 66340 | D13: 156.858 | E13: 7.81 | F13: =B13/C13 -> 2.1141091 | G13: =(B13/D13)*100 -> 89412.08 | H13: =(B13-B12)/B12 -> 0.050758569 | I13: =(C13-C12)/C12 -> 0.014683389 | J13: =LN(B13) -> 11.851182 | K13: =LN(C13) -> 11.102548 | L13: =(F13/$F$2)*100 -> 154.45351 | M13: =E13*F13 -> 16.511192
A14: 1997 | B14: 145000 | C14: 67720 | D14: 160.525 | E14: 7.6 | F14: =B14/C14 -> 2.1411695 | G14: =(B14/D14)*100 -> 90328.609 | H14: =(B14-B13)/B13 -> 0.033868093 | I14: =(C14-C13)/C13 -> 0.020801929 | J14: =LN(B14) -> 11.884489 | K14: =LN(C14) -> 11.123137 | L14: =(F14/$F$2)*100 -> 156.4305 | M14: =E14*F14 -> 16.272888
... A41: 2024 | B41: 418975 | C41: 83730 | D41: 313.698 | E41: 6.72 | F41: =B41/C41 -> 5.0038815 | G41: =(B41/D41)*100 -> 133559.98 | H41: =(B41-B40)/B40 -> -0.01770119 | I41: =(C41-C40)/C40 -> 0.012577095 | J41: =LN(B41) -> 12.945567 | K41: =LN(C41) -> 11.335353 | L41: =(F41/$F$2)*100 -> 365.57578 | M41: =E41*F41 -> 33.626084

Sheet Indices
A1: Year | B1: Income Index | C1: Home Price Index | D1: Affordability Gap Index | E1: Real Price Index (CPI Adjusted)
A2: ='Raw Series'!A3 -> 1985 | B2: =('Transformed Series'!C2/'Transformed Series'!$C$2)*100 -> 100 | C2: =('Transformed Series'!B2/'Transformed Series'!$B$2)*100 -> 100 | D2: =(C2/B2)*100 -> 100 | E2: =('Transformed Series'!G2/'Transformed Series'!$G$2)*100 -> 100
A3: ='Raw Series'!A4 -> 1986 | B3: =('Transformed Series'!C3/'Transformed Series'!$C$2)*100 -> 103.7031 | C3: =('Transformed Series'!B3/'Transformed Series'!$B$2)*100 -> 109.19608 | D3: =(C3/B3)*100 -> 105.29683 | E3: =('Transformed Series'!G3/'Transformed Series'!$G$2)*100 -> 107.11354
A4: ='Raw Series'!A5 -> 1987 | B4: =('Transformed Series'!C4/'Transformed Series'!$C$2)*100 -> 105.00244 | C4: =('Transformed Series'!B4/'Transformed Series'!$B$2)*100 -> 124.23613 | D4: =(C4/B4)*100 -> 118.31738 | E4: =('Transformed Series'!G4/'Transformed Series'!$G$2)*100 -> 117.65676
A5: ='Raw Series'!A6 -> 1988 | B5: =('Transformed Series'!C5/'Transformed Series'!$C$2)*100 -> 105.78204 | C5: =('Transformed Series'!B5/'Transformed Series'!$B$2)*100 -> 133.16523 | D5: =(C5/B5)*100 -> 125.88643 | E5: =('Transformed Series'!G5/'Transformed Series'!$G$2)*100 -> 121.1463
A6: ='Raw Series'!A7 -> 1989 | B6: =('Transformed Series'!C6/'Transformed Series'!$C$2)*100 -> 107.58486 | C6: =('Transformed Series'!B6/'Transformed Series'!$B$2)*100 -> 142.89528 | D6: =(C6/B6)*100 -> 132.82099 | E6: =('Transformed Series'!G6/'Transformed Series'!$G$2)*100 -> 124.05426
A7: ='Raw Series'!A8 -> 1990 | B7: =('Transformed Series'!C7/'Transformed Series'!$C$2)*100 -> 106.28553 | C7: =('Transformed Series'!B7/'Transformed Series'!$B$2)*100 -> 145.12014 | D7: =(C7/B7)*100 -> 136.53801 | E7: =('Transformed Series'!G7/'Transformed Series'!$G$2)*100 -> 119.50992
A8: ='Raw Series'!A9 -> 1991 | B8: =('Transformed Series'!C8/'Transformed Series'!$C$2)*100 -> 103.18337 | C8: =('Transformed Series'!B8/'Transformed Series'!$B$2)*100 -> 142.36132 | D8: =(C8/B8)*100 -> 137.96925 | E8: =('Transformed Series'!G8/'Transformed Series'!$G$2)*100 -> 112.49479
A9: ='Raw Series'!A10 -> 1992 | B9: =('Transformed Series'!C9/'Transformed Series'!$C$2)*100 -> 102.3388 | C9: =('Transformed Series'!B9/'Transformed Series'!$B$2)*100 -> 144.02255 | D9: =(C9/B9)*100 -> 140.73112 | E9: =('Transformed Series'!G9/'Transformed Series'!$G$2)*100 -> 110.44863
A10: ='Raw Series'!A11 -> 1993 | B10: =('Transformed Series'!C10/'Transformed Series'!$C$2)*100 -> 101.83531 | C10: =('Transformed Series'!B10/'Transformed Series'!$B$2)*100 -> 150.10383 | D10: =(C10/B10)*100 -> 147.39861 | E10: =('Transformed Series'!G10/'Transformed Series'!$G$2)*100 -> 111.79216
A11: ='Raw Series'!A12 -> 1994 | B11: =('Transformed Series'!C11/'Transformed Series'!$C$2)*100 -> 102.9235 | C11: =('Transformed Series'!B11/'Transformed Series'!$B$2)*100 -> 154.7612 | D11: =(C11/B11)*100 -> 150.36527 | E11: =('Transformed Series'!G11/'Transformed Series'!$G$2)*100 -> 112.34478
A12: ='Raw Series'!A13 -> 1995 | B12: =('Transformed Series'!C12/'Transformed Series'!$C$2)*100 -> 106.18808 | C12: =('Transformed Series'!B12/'Transformed Series'!$B$2)*100 -> 158.3803 | D12: =(C12/B12)*100 -> 149.15074 | E12: =('Transformed Series'!G12/'Transformed Series'!$G$2)*100 -> 111.83479
A13: ='Raw Series'!A14 -> 1996 | B13: =('Transformed Series'!C13/'Transformed Series'!$C$2)*100 -> 107.74728 | C13: =('Transformed Series'!B13/'Transformed Series'!$B$2)*100 -> 166.41946 | D13: =(C13/B13)*100 -> 154.45351 | E13: =('Transformed Series'!G13/'Transformed Series'!$G$2)*100 -> 114.15888
... A41: ='Raw Series'!A42 -> 2024 | B41: =('Transformed Series'!C41/'Transformed Series'!$C$2)*100 -> 135.99155 | C41: =('Transformed Series'!B41/'Transformed Series'!$B$2)*100 -> 497.15218 | D41: =(C41/B41)*100 -> 365.57578 | E41: =('Transformed Series'!G41/'Transformed Series'!$G$2)*100 -> 170.52571

Sheet Dashboard
B1: U.S. Housing Affordability Dashboard (1985-2024)
B3: Indexed analysis of home prices, income, and affordability divergence
B5: Home Price Growth | D5: Income Growth
B6: 1985-2024 | D6: 1985-2024
B7: =('Transformed Series'!B41-'Transformed Series'!B2)/'Transformed Series'!B2 -> 3.9715218 | D7: =('Transformed Series'!C41-'Transformed Series'!C2)/'Transformed Series'!C2 -> 0.35991554
B8: Affordability Gap Index (Base 1985 = 100)
B9: 2024
B10: =Indices!D41 -> 365.57578
B30: KEY INTERPRETATION Housing prices have increased at a structurally faster rate than income since 1985, resulting in a persistent widening of the affordability gap. This divergence is not fully explained by inflation, as real housing price indices also show sustained upward pressure. The data suggests a structural imbalance between housing supply and demand conditions rather than a short-run cyclical fluctuation.
